felixlib/LICENSE
felixlib/README.md
felixlib/__init__.py
felixlib/__main__.py
felixlib/_build_cython.cp311-win_amd64.pyd
felixlib/_build_pyi.cp311-win_amd64.pyd
felixlib/_build_setup.cp311-win_amd64.pyd
felixlib/_restapi_v1.cp311-win_amd64.pyd
felixlib/_restapi_vs.cp311-win_amd64.pyd
felixlib/_ui.cp311-win_amd64.pyd
felixlib/_ui_dpg.cp311-win_amd64.pyd
felixlib/_ui_dpg_base.cp311-win_amd64.pyd
felixlib/_ui_sg.cp311-win_amd64.pyd
felixlib/_ui_webview.cp311-win_amd64.pyd
felixlib/acad.cp311-win_amd64.pyd
felixlib/ansys.cp311-win_amd64.pyd
felixlib/ansys_gui.cp311-win_amd64.pyd
felixlib/auto.cp311-win_amd64.pyd
felixlib/console.cp311-win_amd64.pyd
felixlib/const.cp311-win_amd64.pyd
felixlib/data_analysis.cp311-win_amd64.pyd
felixlib/elevate.cp311-win_amd64.pyd
felixlib/elevate2.cp311-win_amd64.pyd
felixlib/excel.cp311-win_amd64.pyd
felixlib/general.cp311-win_amd64.pyd
felixlib/general2.cp311-win_amd64.pyd
felixlib/init.cp311-win_amd64.pyd
felixlib/inventor.cp311-win_amd64.pyd
felixlib/latex.cp311-win_amd64.pyd
felixlib/main.cp311-win_amd64.pyd
felixlib/markdown.cp311-win_amd64.pyd
felixlib/restapi.cp311-win_amd64.pyd
felixlib/thread_proc.cp311-win_amd64.pyd
felixlib/todo.cp311-win_amd64.pyd
felixlib/tqdm.cp311-win_amd64.pyd
felixlib/ui.cp311-win_amd64.pyd
felixlib/win_com.cp311-win_amd64.pyd
felixlib-0.0.46.dist-info/LICENSE
felixlib-0.0.46.dist-info/METADATA
felixlib-0.0.46.dist-info/WHEEL
felixlib-0.0.46.dist-info/top_level.txt
felixlib-0.0.46.dist-info/RECORD
