Metadata-Version: 2.1
Name: felixlib
Version: 0.0.46
Summary: Common functions shared by Felix's other packages
Author: spectereye
Author-email: spectereye@gmail.com
License: Copyright (C) spectereye@gmail.com
Requires-Python: >=3.7
License-File: felixlib/LICENSE
